TubeDownloader/TubeDownloader.py
TubeDownloader/__init__.py
TubeDownloader/img/icon.ico
TubeDownloader/img/icon.png
src/TubeDownloader.py
src/__init__.py
TubeDownloader-0.2.1.dist-info/LICENSE
TubeDownloader-0.2.1.dist-info/METADATA
TubeDownloader-0.2.1.dist-info/WHEEL
TubeDownloader-0.2.1.dist-info/top_level.txt
TubeDownloader-0.2.1.dist-info/RECORD
