Metadata-Version: 2.1
Name: TubeDownloader
Version: 0.2.1
Summary: Download audio track of youtube video
Home-page: https://github.com/victordpc/TubeDownloader
Author: victordpc
Author-email: victordpc@gmail.com
License: LGPL v3
Keywords: youtube,download,audio
Platform: UNKNOWN
Classifier: Development Status :: 4 - Beta
Classifier: Programming Language :: Python :: 3.8
Classifier: License :: OSI Approved :: GNU General Public License v3 (GPLv3)
Classifier: Topic :: Multimedia :: Sound/Audio
Requires-Dist: pytube3
